{
	"Females": [
		{
			"Name": "Output 1",
			"PinType": "NEMA 5-15"
		},
		{
			"Name": "Output 2",
			"PinType": "NEMA 5-15"
		},
		{
			"Name": "Output 3",
			"PinType": "NEMA 5-15"
		},
		{
			"Name": "Output 4",
			"PinType": "NEMA 5-15"
		},
		{
			"Name": "Output 5",
			"PinType": "NEMA 5-15"
		},
		{
			"Name": "Output 6",
			"PinType": "NEMA 5-15"
		},
		{
			"Name": "Output 7",
			"PinType": "NEMA 5-15"
		},
		{
			"Name": "Output 8",
			"PinType": "NEMA 5-15"
		}
	],
	"Males": [
		{
			"Name": "Input",
			"PinType": "NEMA 5-15",
			"Protocols": [
				"USB 1.0",
				"USB 1.1",
				"USB 2.0"
			]
		}
	],
	"Name": "Power Strip (8 NEMA 5-15 sockets)"
}